<?xml version="1.0" encoding="utf-8"?>
<Roots >
  <Roots.RootTypes>
    <RootType FullName="Windows.UI.Xaml.Controls.UserControl">
      <RootProperty Name="Resources" />
      <RootProperty Name="Content" />
    </RootType>
    <RootType FullName="Windows.UI.Xaml.Controls.Grid">
      <RootProperty Name="RowDefinitions" />
      <RootProperty Name="ColumnDefinitions" />
      <RootProperty Name="Children" />
      <RootProperty Name="Visibility" />
      <RootProperty Name="Background" />
      <RootProperty Name="Height" />
      <RootProperty Name="Width" />
      <RootProperty Name="MinHeight" />
      <RootProperty Name="MinWidth" />
      <RootProperty Name="Name" />
      <RootProperty Name="BorderBrush" />
      <RootProperty Name="CornerRadius" />
      <RootProperty Name="BorderThickness" />
      <RootProperty Name="Margin" />
      <RootMethod Name="GetRow" />
      <RootMethod Name="SetRow" />
      <RootMethod Name="GetColumn" />
      <RootMethod Name="SetColumn" />
      <RootMethod Name="GetRowSpan" />
      <RootMethod Name="SetRowSpan" />
      <RootMethod Name="GetColumnSpan" />
      <RootMethod Name="SetColumnSpan" />
    </RootType>
    <RootType FullName="Windows.UI.Xaml.Controls.RowDefinition">
      <RootProperty Name="Height" />
    </RootType>
    <RootType FullName="Windows.UI.Xaml.Controls.ColumnDefinition">
      <RootProperty Name="Width" />
    </RootType>
    <RootType FullName="Windows.UI.Xaml.Controls.FlipView">
      <RootProperty Name="Name" />
      <RootProperty Name="UseTouchAnimationsForAllNavigation" />
    </RootType>
    <RootType FullName="Syncfusion.Windows.PdfViewer.PdfFlipView" />
    <RootType FullName="Windows.UI.Xaml.Controls.Canvas">
      <RootProperty Name="Background" />
      <RootProperty Name="Height" />
      <RootProperty Name="Width" />
      <RootProperty Name="ManipulationMode" />
      <RootProperty Name="Visibility" />
      <RootProperty Name="Children" />
      <RootMethod Name="GetLeft" />
      <RootMethod Name="SetLeft" />
      <RootMethod Name="GetTop" />
      <RootMethod Name="SetTop" />
    </RootType>
    <RootType FullName="Windows.UI.Xaml.Controls.Border">
      <RootProperty Name="BorderBrush" />
      <RootProperty Name="BorderThickness" />
      <RootProperty Name="Child" />
      <RootProperty Name="Background" />
    </RootType>
    <RootType FullName="Windows.UI.Xaml.Controls.TextBlock">
      <RootProperty Name="FontWeight" />
      <RootProperty Name="Padding" />
      <RootProperty Name="HorizontalAlignment" />
      <RootProperty Name="MaxWidth" />
      <RootProperty Name="TextWrapping" />
      <RootProperty Name="VerticalAlignment" />
      <RootProperty Name="FontSize" />
      <RootProperty Name="Text" />
      <RootProperty Name="Height" />
      <RootProperty Name="Width" />
      <RootProperty Name="Margin" />
      <RootProperty Name="TextTrimming" />
      <RootProperty Name="Visibility" />
    </RootType>
    <RootType FullName="Windows.UI.Xaml.Controls.TextBox">
      <RootProperty Name="Height" />
      <RootProperty Name="Width" />
      <RootProperty Name="TextWrapping" />
      <RootProperty Name="AcceptsReturn" />
      <RootProperty Name="HorizontalAlignment" />
      <RootProperty Name="Padding" />
      <RootProperty Name="VerticalAlignment" />
      <RootProperty Name="Text" />
    </RootType>
    <RootType FullName="Windows.UI.Xaml.Controls.Button">
      <RootProperty Name="FontSize" />
      <RootProperty Name="VerticalAlignment" />
      <RootProperty Name="Content" />
      <RootProperty Name="Padding" />
      <RootProperty Name="HorizontalAlignment" />
      <RootProperty Name="Name" />
      <RootProperty Name="Style" />
      <RootProperty Name="Height" />
      <RootProperty Name="Width" />
      <RootProperty Name="BorderThickness" />
      <RootProperty Name="Margin" />
      <RootProperty Name="Background" />
      <RootEvent Name="Click" />
    </RootType>
    <RootType FullName="Windows.UI.Xaml.Shapes.Path">
      <RootProperty Name="Data" />
      <RootProperty Name="Fill" />
      <RootProperty Name="Height" />
      <RootProperty Name="Stretch" />
      <RootProperty Name="Width" />
      <RootProperty Name="Margin" />
      <RootProperty Name="RenderTransformOrigin" />
      <RootProperty Name="RenderTransform" />
      <RootProperty Name="Stroke" />
      <RootProperty Name="HorizontalAlignment" />
      <RootProperty Name="UseLayoutRounding" />
    </RootType>
    <RootType FullName="Syncfusion.Windows.PdfViewer.PopupAnnotationHelper" />
    <RootType FullName="Windows.UI.Xaml.Controls.Control">
      <RootProperty Name="Background" />
      <RootProperty Name="Foreground" />
      <RootProperty Name="BorderBrush" />
      <RootProperty Name="BorderThickness" />
      <RootProperty Name="FontFamily" />
      <RootProperty Name="FontWeight" />
      <RootProperty Name="FontSize" />
      <RootProperty Name="Template" />
      <RootProperty Name="TabNavigation" />
      <RootProperty Name="UseSystemFocusVisuals" />
    </RootType>
    <RootType FullName="Windows.UI.Xaml.FrameworkElement">
      <RootProperty Name="HorizontalAlignment" />
      <RootProperty Name="VerticalAlignment" />
      <RootProperty Name="Margin" />
    </RootType>
    <RootType FullName="Windows.UI.Xaml.Setter">
      <RootProperty Name="Property" />
      <RootProperty Name="Value" />
    </RootType>
    <RootType FullName="Windows.UI.Xaml.Controls.ControlTemplate">
      <RootProperty Name="TargetType" />
      <RootProperty Name="Template" />
    </RootType>
    <RootType FullName="Windows.UI.Xaml.VisualStateManager">
      <RootMethod Name="GetVisualStateGroups" />
    </RootType>
    <RootType FullName="Windows.UI.Xaml.VisualStateGroup">
      <RootProperty Name="States" />
    </RootType>
    <RootType FullName="Windows.UI.Xaml.VisualState">
      <RootProperty Name="Storyboard" />
    </RootType>
    <RootType FullName="Windows.UI.Xaml.Media.Animation.Storyboard">
      <RootProperty Name="Children" />
      <RootMethod Name="GetTargetName" />
      <RootMethod Name="SetTargetName" />
      <RootMethod Name="GetTargetProperty" />
      <RootMethod Name="SetTargetProperty" />
    </RootType>
    <RootType FullName="Windows.UI.Xaml.Media.Animation.DoubleAnimation">
      <RootProperty Name="To" />
      <RootProperty Name="Duration" />
    </RootType>
    <RootType FullName="Windows.UI.Xaml.Controls.ContentPresenter">
      <RootProperty Name="Content" />
      <RootProperty Name="ContentTransitions" />
      <RootProperty Name="ContentTemplate" />
      <RootProperty Name="Margin" />
      <RootProperty Name="HorizontalAlignment" />
      <RootProperty Name="VerticalAlignment" />
    </RootType>
    <RootType FullName="Windows.UI.Xaml.Automation.AutomationProperties">
      <RootMethod Name="GetAccessibilityView" />
      <RootMethod Name="SetAccessibilityView" />
    </RootType>
    <RootType FullName="Microsoft.Xaml.DirectUI.ProxyTypes.TemplateBindingExtension" />
    <RootType FullName="Microsoft.Xaml.DirectUI.ProxyTypes.ThemeResourceExtension" />
    <RootType FullName="Windows.UI.Xaml.Controls.Viewbox">
      <RootProperty Name="Child" />
    </RootType>
    <RootType FullName="Microsoft.Xaml.DirectUI.ProxyTypes.StaticResourceExtension" />
    <RootType FullName="Windows.UI.Xaml.Media.TransformGroup">
      <RootProperty Name="Children" />
    </RootType>
    <RootType FullName="Windows.UI.Xaml.Media.RotateTransform">
      <RootProperty Name="Angle" />
    </RootType>
    <RootType FullName="Windows.UI.Xaml.Media.ScaleTransform">
      <RootProperty Name="ScaleX" />
      <RootProperty Name="ScaleY" />
    </RootType>
    <RootType FullName="Windows.UI.Xaml.Shapes.Ellipse">
      <RootProperty Name="Name" />
      <RootProperty Name="Fill" />
      <RootProperty Name="Visibility" />
    </RootType>
    <RootType FullName="Syncfusion.Windows.PdfViewer.TextSelectionCopyButton" />
    <RootType FullName="Windows.UI.Xaml.Controls.GridViewItem" />
    <RootType FullName="Windows.UI.Xaml.UIElement">
      <RootProperty Name="IsHoldingEnabled" />
      <RootProperty Name="ManipulationMode" />
    </RootType>
    <RootType FullName="Windows.UI.Xaml.Controls.Primitives.GridViewItemPresenter">
      <RootProperty Name="PointerOverBackground" />
    </RootType>
    <RootType FullName="Windows.UI.Xaml.Controls.GridView">
      <RootProperty Name="Background" />
      <RootProperty Name="CanDragItems" />
      <RootProperty Name="AllowDrop" />
      <RootProperty Name="IsItemClickEnabled" />
      <RootProperty Name="SelectionMode" />
      <RootProperty Name="VerticalAlignment" />
      <RootProperty Name="BorderThickness" />
      <RootProperty Name="ItemContainerStyle" />
      <RootProperty Name="Name" />
      <RootProperty Name="ShowsScrollingPlaceholders" />
      <RootProperty Name="IsSwipeEnabled" />
      <RootProperty Name="Items" />
      <RootEvent Name="Loaded" />
    </RootType>
    <RootType FullName="Windows.UI.Xaml.Controls.ScrollViewer">
      <RootProperty Name="Background" />
      <RootProperty Name="IsHorizontalScrollChainingEnabled" />
      <RootProperty Name="Margin" />
      <RootProperty Name="HorizontalScrollBarVisibility" />
      <RootProperty Name="VerticalScrollBarVisibility" />
      <RootProperty Name="VerticalScrollMode" />
      <RootProperty Name="HorizontalScrollMode" />
      <RootProperty Name="MaxZoomFactor" />
      <RootProperty Name="MinZoomFactor" />
      <RootProperty Name="ZoomMode" />
      <RootProperty Name="Content" />
      <RootMethod Name="GetIsHorizontalScrollChainingEnabled" />
      <RootMethod Name="SetIsHorizontalScrollChainingEnabled" />
      <RootMethod Name="GetVerticalScrollBarVisibility" />
      <RootMethod Name="SetVerticalScrollBarVisibility" />
      <RootMethod Name="GetHorizontalScrollBarVisibility" />
      <RootMethod Name="SetHorizontalScrollBarVisibility" />
      <RootMethod Name="GetHorizontalScrollMode" />
      <RootMethod Name="SetHorizontalScrollMode" />
    </RootType>
    <RootType FullName="Syncfusion.Windows.PdfViewer.ThumbnailView" />
    <RootType FullName="Windows.UI.Xaml.ResourceDictionary" />
    <RootType FullName="Windows.UI.Xaml.Controls.Primitives.Thumb">
      <RootProperty Name="Background" />
      <RootProperty Name="DataContext" />
      <RootProperty Name="Height" />
      <RootProperty Name="Style" />
      <RootProperty Name="Width" />
      <RootProperty Name="Visibility" />
    </RootType>
    <RootType FullName="Syncfusion.UI.Xaml.Controls.Input.SfRangeSlider">
      <RootProperty Name="Name" />
      <RootProperty Name="Margin" />
      <RootProperty Name="VerticalAlignment" />
      <RootProperty Name="HorizontalAlignment" />
      <RootProperty Name="Style" />
    </RootType>
    <RootType FullName="Windows.UI.Xaml.Controls.Primitives.RangeBase">
      <RootProperty Name="Maximum" />
      <RootProperty Name="SmallChange" />
    </RootType>
    <RootType FullName="Syncfusion.UI.Xaml.Controls.Input.TickBar">
      <RootProperty Name="IsEnabled" />
      <RootProperty Name="IsHitTestVisible" />
      <RootProperty Name="HorizontalAlignment" />
      <RootProperty Name="Margin" />
      <RootProperty Name="Visibility" />
      <RootProperty Name="Fill" />
      <RootProperty Name="Maximum" />
      <RootProperty Name="Minimum" />
      <RootProperty Name="Orientation" />
      <RootProperty Name="TickFrequency" />
      <RootProperty Name="LabelPlacement" />
      <RootProperty Name="ValuePlacement" />
      <RootProperty Name="TickPlacement" />
      <RootProperty Name="ShowCustomLabels" />
      <RootProperty Name="ShowValueLabels" />
      <RootProperty Name="CustomLabels" />
      <RootProperty Name="IsDirectionReversed" />
      <RootProperty Name="LabelOrientation" />
      <RootProperty Name="VerticalAlignment" />
    </RootType>
    <RootType FullName="Syncfusion.UI.Xaml.Controls.Input.TickBarItem" />
    <RootType FullName="Syncfusion.Windows.PdfViewer.SfPdfViewerControl" />
    <RootType FullName="Syncfusion.Windows.PdfViewer.PdfDocumentView" />
    <RootType FullName="Windows.UI.Xaml.Controls.SemanticZoom">
      <RootProperty Name="Name" />
      <RootProperty Name="IsZoomOutButtonEnabled" />
      <RootProperty Name="ZoomedInView" />
      <RootProperty Name="ZoomedOutView" />
    </RootType>
    <RootType FullName="Windows.UI.Xaml.Controls.ProgressRing">
      <RootProperty Name="Name" />
      <RootProperty Name="IsActive" />
      <RootProperty Name="Foreground" />
      <RootProperty Name="Height" />
      <RootProperty Name="Width" />
      <RootProperty Name="Visibility" />
    </RootType>
    <RootType FullName="Windows.UI.Xaml.Controls.StackPanel">
      <RootProperty Name="HorizontalAlignment" />
      <RootProperty Name="VerticalAlignment" />
      <RootProperty Name="Children" />
    </RootType>
    <RootType FullName="Windows.UI.Xaml.Shapes.Line">
      <RootProperty Name="X1" />
      <RootProperty Name="X2" />
      <RootProperty Name="Opacity" />
      <RootProperty Name="Y1" />
      <RootProperty Name="Y2" />
      <RootProperty Name="StrokeThickness" />
      <RootProperty Name="Stroke" />
      <RootProperty Name="VerticalAlignment" />
      <RootProperty Name="HorizontalAlignment" />
    </RootType>
    <RootType FullName="Windows.UI.Xaml.Shapes.Rectangle">
      <RootProperty Name="Width" />
      <RootProperty Name="Fill" />
      <RootProperty Name="Height" />
    </RootType>
  </Roots.RootTypes>
</Roots>
